[
  {
    "id": "3200",
    "lineRef": "KOL:Line:8_6402",
    "lat": 59.1757165,
    "lon": 6.0772908,
    "lastUpdated": "2026-01-29T12:57:06Z"
  },
  {
    "id": "258009600",
    "lineRef": "KOL:Line:8_5200",
    "lat": 58.972031,
    "lon": 5.7766049,
    "lastUpdated": "2026-01-29T12:57:06Z"
  },
  {
    "id": "3215",
    "lineRef": "KOL:Line:8_6403",
    "lat": 59.1755412,
    "lon": 6.0773498,
    "lastUpdated": "2026-01-29T12:57:06Z"
  },
  {
    "id": "3286",
    "lineRef": "KOL:Line:8_6130",
    "lat": 59.0362225,
    "lon": 5.9361478,
    "lastUpdated": "2026-01-29T12:52:43Z"
  },
  {
    "id": "3271",
    "lineRef": "KOL:Line:8_6121",
    "lat": 58.9012667,
    "lon": 6.1152632,
    "lastUpdated": "2026-01-29T12:57:06Z"
  },
  {
    "id": "3275",
    "lineRef": "KOL:Line:8_6203",
    "lat": 58.899736,
    "lon": 6.1439588,
    "lastUpdated": "2026-01-29T12:57:05Z"
  },
  {
    "id": "258002060",
    "lineRef": "KOL:Line:26_5958",
    "lat": 59.26121166666667,
    "lon": 6.159518333333334,
    "lastUpdated": "2026-01-29T12:56:55.231Z"
  },
  {
    "id": "3301",
    "lineRef": "KOL:Line:8_9903",
    "lat": 58.9339995,
    "lon": 5.7024805,
    "lastUpdated": "2026-01-29T12:50:30Z"
  },
  {
    "id": "3312",
    "lineRef": "KOL:Line:8_2600",
    "lat": 58.5337888,
    "lon": 6.148564,
    "lastUpdated": "2026-01-29T12:50:58Z"
  },
  {
    "id": "3311",
    "lineRef": "KOL:Line:8_2631",
    "lat": 58.6893383,
    "lon": 6.1777377,
    "lastUpdated": "2026-01-29T12:57:06Z"
  },
  {
    "id": "3313",
    "lineRef": "KOL:Line:8_2018",
    "lat": 58.7830512,
    "lon": 5.7150133,
    "lastUpdated": "2026-01-29T12:57:05Z"
  },
  {
    "id": "3308",
    "lineRef": "KOL:Line:8_2024",
    "lat": 58.7722187,
    "lon": 5.6773956,
    "lastUpdated": "2026-01-29T12:57:06Z"
  },
  {
    "id": "3307",
    "lineRef": "KOL:Line:8_2670",
    "lat": 58.7775325,
    "lon": 5.6813857,
    "lastUpdated": "2026-01-29T12:57:06Z"
  },
  {
    "id": "3306",
    "lineRef": "KOL:Line:8_2656",
    "lat": 58.66916,
    "lon": 5.6512867,
    "lastUpdated": "2026-01-29T12:57:06Z"
  },
  {
    "id": "2013",
    "lineRef": "KOL:Line:8_1012",
    "lat": 58.891113,
    "lon": 5.6696025,
    "lastUpdated": "2026-01-29T12:57:05Z"
  },
  {
    "id": "2011",
    "lineRef": "KOL:Line:8_1004",
    "lat": 58.9472092,
    "lon": 5.7435797,
    "lastUpdated": "2026-01-29T12:57:06Z"
  },
  {
    "id": "2012",
    "lineRef": "KOL:Line:8_1004",
    "lat": 58.9311032,
    "lon": 5.7380468,
    "lastUpdated": "2026-01-29T12:57:06Z"
  },
  {
    "id": "2017",
    "lineRef": "KOL:Line:8_1007",
    "lat": 58.9463002,
    "lon": 5.6809795,
    "lastUpdated": "2026-01-29T12:57:06Z"
  },
  {
    "id": "2015",
    "lineRef": "KOL:Line:8_1004",
    "lat": 58.9542055,
    "lon": 5.6887137,
    "lastUpdated": "2026-01-29T12:57:06Z"
  },
  {
    "id": "2016",
    "lineRef": "KOL:Line:8_1002",
    "lat": 58.9091105,
    "lon": 5.7282412,
    "lastUpdated": "2026-01-29T12:57:06Z"
  },
  {
    "id": "2010",
    "lineRef": "KOL:Line:8_1004",
    "lat": 58.9517238,
    "lon": 5.6578953,
    "lastUpdated": "2026-01-29T12:57:06Z"
  },
  {
    "id": "2008",
    "lineRef": "KOL:Line:8_1002",
    "lat": 58.9190002,
    "lon": 5.6050213,
    "lastUpdated": "2026-01-29T12:57:06Z"
  },
  {
    "id": "2003",
    "lineRef": "KOL:Line:8_1025",
    "lat": 58.877128,
    "lon": 5.725147,
    "lastUpdated": "2026-01-29T12:57:06Z"
  },
  {
    "id": "2000",
    "lineRef": "KOL:Line:8_1002",
    "lat": 58.8507477,
    "lon": 5.7347007,
    "lastUpdated": "2026-01-29T12:57:06Z"
  },
  {
    "id": "2001",
    "lineRef": "KOL:Line:8_1009",
    "lat": 58.9690307,
    "lon": 5.7309132,
    "lastUpdated": "2026-01-29T12:57:00Z"
  },
  {
    "id": "2004",
    "lineRef": "KOL:Line:8_1007",
    "lat": 58.9672872,
    "lon": 5.7237885,
    "lastUpdated": "2026-01-29T12:57:06Z"
  },
  {
    "id": "2005",
    "lineRef": "KOL:Line:8_1012",
    "lat": 58.8803997,
    "lon": 5.7263512,
    "lastUpdated": "2026-01-29T12:57:06Z"
  },
  {
    "id": "2035",
    "lineRef": "KOL:Line:8_1002",
    "lat": 58.8759372,
    "lon": 5.7246978,
    "lastUpdated": "2026-01-29T12:57:06Z"
  },
  {
    "id": "2033",
    "lineRef": "KOL:Line:8_1010",
    "lat": 58.9392373,
    "lon": 5.6467103,
    "lastUpdated": "2026-01-29T12:57:05Z"
  },
  {
    "id": "2031",
    "lineRef": "KOL:Line:8_1004",
    "lat": 58.9052508,
    "lon": 5.6980515,
    "lastUpdated": "2026-01-29T12:56:42Z"
  },
  {
    "id": "2024",
    "lineRef": "KOL:Line:8_1008",
    "lat": 58.8794608,
    "lon": 5.6693544,
    "lastUpdated": "2026-01-29T12:51:57Z"
  },
  {
    "id": "2025",
    "lineRef": "KOL:Line:8_1008",
    "lat": 58.9403217,
    "lon": 5.6928318,
    "lastUpdated": "2026-01-29T12:57:06Z"
  },
  {
    "id": "2022",
    "lineRef": "KOL:Line:8_1004",
    "lat": 58.9156007,
    "lon": 5.7295497,
    "lastUpdated": "2026-01-29T12:57:06Z"
  },
  {
    "id": "2023",
    "lineRef": "KOL:Line:8_1002",
    "lat": 58.88752,
    "lon": 5.7289327,
    "lastUpdated": "2026-01-29T12:57:05Z"
  },
  {
    "id": "2027",
    "lineRef": "KOL:Line:8_1004",
    "lat": 58.8969677,
    "lon": 5.740011,
    "lastUpdated": "2026-01-29T12:57:06Z"
  },
  {
    "id": "2020",
    "lineRef": "KOL:Line:8_1002",
    "lat": 58.9615438,
    "lon": 5.7374515,
    "lastUpdated": "2026-01-29T12:57:06Z"
  },
  {
    "id": "2021",
    "lineRef": "KOL:Line:8_1007",
    "lat": 58.967831,
    "lon": 5.7279763,
    "lastUpdated": "2026-01-29T12:57:06Z"
  },
  {
    "id": "2019",
    "lineRef": "KOL:Line:8_1002",
    "lat": 58.8701252,
    "lon": 5.7262732,
    "lastUpdated": "2026-01-29T12:57:06Z"
  },
  {
    "id": "3389",
    "lineRef": "KOL:Line:8_2630",
    "lat": 58.4921095,
    "lon": 6.359734,
    "lastUpdated": "2026-01-29T12:57:06Z"
  },
  {
    "id": "258021190",
    "lineRef": "KOL:Line:8_5961",
    "lat": 59.064816666666665,
    "lon": 5.908343333333334,
    "lastUpdated": "2026-01-29T12:57:02.16Z"
  },
  {
    "id": "2110",
    "lineRef": "KOL:Line:8_1013",
    "lat": 58.9679398,
    "lon": 5.7312728,
    "lastUpdated": "2026-01-29T12:55:57Z"
  },
  {
    "id": "2109",
    "lineRef": "KOL:Line:8_1013",
    "lat": 59.0969423,
    "lon": 5.6985197,
    "lastUpdated": "2026-01-29T12:57:06Z"
  },
  {
    "id": "2108",
    "lineRef": "KOL:Line:8_1019",
    "lat": 59.0024805,
    "lon": 5.6296623,
    "lastUpdated": "2026-01-29T12:48:41Z"
  },
  {
    "id": "2103",
    "lineRef": "KOL:Line:8_1016",
    "lat": 59.0966042,
    "lon": 5.6978485,
    "lastUpdated": "2026-01-29T12:52:36Z"
  },
  {
    "id": "2212",
    "lineRef": "KOL:Line:8_1002",
    "lat": 58.9348537,
    "lon": 5.5916403,
    "lastUpdated": "2026-01-29T12:57:06Z"
  },
  {
    "id": "2215",
    "lineRef": "KOL:Line:8_1038",
    "lat": 58.9545192,
    "lon": 5.7421348,
    "lastUpdated": "2026-01-29T12:57:06Z"
  },
  {
    "id": "2214",
    "lineRef": "KOL:Line:8_1007",
    "lat": 58.9124993,
    "lon": 5.7263905,
    "lastUpdated": "2026-01-29T12:57:06Z"
  },
  {
    "id": "2208",
    "lineRef": "KOL:Line:8_1011",
    "lat": 59.0106693,
    "lon": 5.6428693,
    "lastUpdated": "2026-01-29T12:57:05Z"
  },
  {
    "id": "2209",
    "lineRef": "KOL:Line:8_1000",
    "lat": 58.9702918,
    "lon": 5.7351375,
    "lastUpdated": "2026-01-29T12:57:05Z"
  },
  {
    "id": "2200",
    "lineRef": "KOL:Line:8_1004",
    "lat": 58.948492,
    "lon": 5.7433202,
    "lastUpdated": "2026-01-29T12:57:06Z"
  },
  {
    "id": "2204",
    "lineRef": "KOL:Line:8_1006",
    "lat": 58.9209881,
    "lon": 5.7036504,
    "lastUpdated": "2026-01-29T12:57:06Z"
  },
  {
    "id": "2205",
    "lineRef": "KOL:Line:8_1002",
    "lat": 58.963352,
    "lon": 5.7262817,
    "lastUpdated": "2026-01-29T12:57:06Z"
  },
  {
    "id": "2203",
    "lineRef": "KOL:Line:8_1002",
    "lat": 58.9259458,
    "lon": 5.7346265,
    "lastUpdated": "2026-01-29T12:57:06Z"
  },
  {
    "id": "2234",
    "lineRef": "KOL:Line:8_1038",
    "lat": 58.8795361,
    "lon": 5.7260752,
    "lastUpdated": "2026-01-29T12:57:05Z"
  },
  {
    "id": "2231",
    "lineRef": "KOL:Line:8_1007",
    "lat": 58.8515695,
    "lon": 5.7369457,
    "lastUpdated": "2026-01-29T12:57:06Z"
  },
  {
    "id": "2237",
    "lineRef": "KOL:Line:8_1004",
    "lat": 58.9629145,
    "lon": 5.735799,
    "lastUpdated": "2026-01-29T12:57:05Z"
  },
  {
    "id": "2238",
    "lineRef": "KOL:Line:8_1000",
    "lat": 58.9669648,
    "lon": 5.7334255,
    "lastUpdated": "2026-01-29T12:54:57Z"
  },
  {
    "id": "2230",
    "lineRef": "KOL:Line:8_1000",
    "lat": 59.0048358,
    "lon": 5.7256245,
    "lastUpdated": "2026-01-29T12:57:06Z"
  },
  {
    "id": "2228",
    "lineRef": "KOL:Line:8_1004",
    "lat": 58.9052438,
    "lon": 5.6978998,
    "lastUpdated": "2026-01-29T12:48:57Z"
  },
  {
    "id": "2222",
    "lineRef": "KOL:Line:8_1000",
    "lat": 58.9701507,
    "lon": 5.7485474,
    "lastUpdated": "2026-01-29T12:57:06Z"
  },
  {
    "id": "2223",
    "lineRef": "KOL:Line:8_1006",
    "lat": 58.9931217,
    "lon": 5.6895715,
    "lastUpdated": "2026-01-29T12:57:05Z"
  },
  {
    "id": "2220",
    "lineRef": "KOL:Line:8_2007",
    "lat": 58.8384793,
    "lon": 5.7733107,
    "lastUpdated": "2026-01-29T12:57:06Z"
  },
  {
    "id": "2221",
    "lineRef": "KOL:Line:8_1000",
    "lat": 58.9714282,
    "lon": 5.740935,
    "lastUpdated": "2026-01-29T12:57:06Z"
  },
  {
    "id": "2226",
    "lineRef": "KOL:Line:8_1000",
    "lat": 59.0023612,
    "lon": 5.7193638,
    "lastUpdated": "2026-01-29T12:57:06Z"
  },
  {
    "id": "2224",
    "lineRef": "KOL:Line:8_1011",
    "lat": 59.0017592,
    "lon": 5.618547,
    "lastUpdated": "2026-01-29T12:57:06Z"
  },
  {
    "id": "2225",
    "lineRef": "KOL:Line:8_2004",
    "lat": 58.8301607,
    "lon": 5.7158318,
    "lastUpdated": "2026-01-29T12:57:05Z"
  },
  {
    "id": "2219",
    "lineRef": "KOL:Line:8_1038",
    "lat": 58.9390502,
    "lon": 5.6927772,
    "lastUpdated": "2026-01-29T12:57:05Z"
  },
  {
    "id": "2254",
    "lineRef": "KOL:Line:8_1002",
    "lat": 58.851269,
    "lon": 5.7361515,
    "lastUpdated": "2026-01-29T12:55:59Z"
  },
  {
    "id": "2257",
    "lineRef": "KOL:Line:8_1002",
    "lat": 58.9300825,
    "lon": 5.6075588,
    "lastUpdated": "2026-01-29T12:57:06Z"
  },
  {
    "id": "2258",
    "lineRef": "KOL:Line:8_1006",
    "lat": 58.9783792,
    "lon": 5.6986437,
    "lastUpdated": "2026-01-29T12:57:06Z"
  },
  {
    "id": "2251",
    "lineRef": "KOL:Line:8_1011",
    "lat": 58.9683053,
    "lon": 5.7310215,
    "lastUpdated": "2026-01-29T12:57:06Z"
  },
  {
    "id": "2252",
    "lineRef": "KOL:Line:8_1011",
    "lat": 58.9911715,
    "lon": 5.6750297,
    "lastUpdated": "2026-01-29T12:57:06Z"
  },
  {
    "id": "2244",
    "lineRef": "KOL:Line:8_1006",
    "lat": 58.8698718,
    "lon": 5.7263588,
    "lastUpdated": "2026-01-29T12:57:06Z"
  },
  {
    "id": "2245",
    "lineRef": "KOL:Line:8_1007",
    "lat": 58.8566655,
    "lon": 5.741352,
    "lastUpdated": "2026-01-29T12:57:06Z"
  },
  {
    "id": "2242",
    "lineRef": "KOL:Line:8_1006",
    "lat": 58.849738,
    "lon": 5.7329422,
    "lastUpdated": "2026-01-29T12:57:06Z"
  },
  {
    "id": "2243",
    "lineRef": "KOL:Line:8_1038",
    "lat": 58.9934751,
    "lon": 5.7333919,
    "lastUpdated": "2026-01-29T12:47:12Z"
  },
  {
    "id": "2248",
    "lineRef": "KOL:Line:8_1006",
    "lat": 58.9574828,
    "lon": 5.7399652,
    "lastUpdated": "2026-01-29T12:57:06Z"
  },
  {
    "id": "2249",
    "lineRef": "KOL:Line:8_1012",
    "lat": 58.8843792,
    "lon": 5.6224763,
    "lastUpdated": "2026-01-29T12:57:06Z"
  },
  {
    "id": "2246",
    "lineRef": "KOL:Line:8_1006",
    "lat": 58.977873,
    "lon": 5.7029387,
    "lastUpdated": "2026-01-29T12:57:06Z"
  },
  {
    "id": "2247",
    "lineRef": "KOL:Line:8_1007",
    "lat": 58.9805408,
    "lon": 5.6914755,
    "lastUpdated": "2026-01-29T12:57:06Z"
  },
  {
    "id": "2240",
    "lineRef": "KOL:Line:8_1011",
    "lat": 58.9728952,
    "lon": 5.7224198,
    "lastUpdated": "2026-01-29T12:57:06Z"
  },
  {
    "id": "2241",
    "lineRef": "KOL:Line:8_1004",
    "lat": 58.954063,
    "lon": 5.6899032,
    "lastUpdated": "2026-01-29T12:57:05Z"
  },
  {
    "id": "2239",
    "lineRef": "KOL:Line:8_1006",
    "lat": 58.9046477,
    "lon": 5.6996608,
    "lastUpdated": "2026-01-29T12:57:06Z"
  },
  {
    "id": "2267",
    "lineRef": "KOL:Line:8_1006",
    "lat": 58.94163,
    "lon": 5.69856,
    "lastUpdated": "2026-01-29T12:57:06Z"
  },
  {
    "id": "2265",
    "lineRef": "KOL:Line:8_1007",
    "lat": 58.8927967,
    "lon": 5.7397063,
    "lastUpdated": "2026-01-29T12:57:06Z"
  },
  {
    "id": "2268",
    "lineRef": "KOL:Line:8_1038",
    "lat": 59.003286,
    "lon": 5.7322878,
    "lastUpdated": "2026-01-29T12:57:06Z"
  },
  {
    "id": "2269",
    "lineRef": "KOL:Line:8_1006",
    "lat": 58.8883152,
    "lon": 5.7284452,
    "lastUpdated": "2026-01-29T12:57:06Z"
  },
  {
    "id": "258000840",
    "lineRef": "KOL:Line:8_5986",
    "lat": 59.170275,
    "lon": 5.878278333333333,
    "lastUpdated": "2026-01-29T12:56:58.581Z"
  },
  {
    "id": "2262",
    "lineRef": "KOL:Line:8_1002",
    "lat": 58.9561737,
    "lon": 5.6983948,
    "lastUpdated": "2026-01-29T12:57:06Z"
  },
  {
    "id": "2263",
    "lineRef": "KOL:Line:8_2007",
    "lat": 58.8511867,
    "lon": 5.7368435,
    "lastUpdated": "2026-01-29T12:57:04Z"
  },
  {
    "id": "2260",
    "lineRef": "KOL:Line:8_1007",
    "lat": 58.9398187,
    "lon": 5.6886988,
    "lastUpdated": "2026-01-29T12:57:06Z"
  },
  {
    "id": "2261",
    "lineRef": "KOL:Line:8_1002",
    "lat": 58.9609703,
    "lon": 5.6238505,
    "lastUpdated": "2026-01-29T12:57:06Z"
  },
  {
    "id": "258223000",
    "lineRef": "KOL:Line:30_1130",
    "lat": 59.158744999999996,
    "lon": 5.530033333333334,
    "lastUpdated": "2026-01-29T12:57:01.91Z"
  },
  {
    "id": "2311",
    "lineRef": "KOL:Line:8_1005",
    "lat": 58.944279,
    "lon": 5.7249527,
    "lastUpdated": "2026-01-29T12:57:06Z"
  },
  {
    "id": "2314",
    "lineRef": "KOL:Line:8_1015",
    "lat": 58.9786257,
    "lon": 5.6972491,
    "lastUpdated": "2026-01-29T12:57:06Z"
  },
  {
    "id": "2315",
    "lineRef": "KOL:Line:8_1029",
    "lat": 58.9684511,
    "lon": 5.7311034,
    "lastUpdated": "2026-01-29T12:56:50Z"
  },
  {
    "id": "2305",
    "lineRef": "KOL:Line:8_1043",
    "lat": 58.9133763,
    "lon": 5.7251648,
    "lastUpdated": "2026-01-29T12:57:06Z"
  },
  {
    "id": "2306",
    "lineRef": "KOL:Line:8_1043",
    "lat": 58.9015168,
    "lon": 5.7078147,
    "lastUpdated": "2026-01-29T12:57:06Z"
  },
  {
    "id": "2309",
    "lineRef": "KOL:Line:8_1005",
    "lat": 58.9451039,
    "lon": 5.6932228,
    "lastUpdated": "2026-01-29T12:57:06Z"
  },
  {
    "id": "2300",
    "lineRef": "KOL:Line:8_1039",
    "lat": 58.8830698,
    "lon": 5.7272848,
    "lastUpdated": "2026-01-29T12:57:06Z"
  },
  {
    "id": "2303",
    "lineRef": "KOL:Line:8_2005",
    "lat": 58.8514845,
    "lon": 5.7364678,
    "lastUpdated": "2026-01-29T12:57:06Z"
  },
  {
    "id": "2304",
    "lineRef": "KOL:Line:8_1008",
    "lat": 58.9465075,
    "lon": 5.680825,
    "lastUpdated": "2026-01-29T12:57:06Z"
  },
  {
    "id": "2301",
    "lineRef": "KOL:Line:8_1012",
    "lat": 58.8833617,
    "lon": 5.6277952,
    "lastUpdated": "2026-01-29T12:57:05Z"
  },
  {
    "id": "2302",
    "lineRef": "KOL:Line:8_1020",
    "lat": 59.0039345,
    "lon": 5.756858,
    "lastUpdated": "2026-01-29T12:56:02Z"
  },
  {
    "id": "2332",
    "lineRef": "KOL:Line:8_1012",
    "lat": 58.8849545,
    "lon": 5.6621075,
    "lastUpdated": "2026-01-29T12:57:06Z"
  },
  {
    "id": "2333",
    "lineRef": "KOL:Line:8_1012",
    "lat": 58.8882943,
    "lon": 5.7286848,
    "lastUpdated": "2026-01-29T12:57:06Z"
  },
  {
    "id": "2330",
    "lineRef": "KOL:Line:8_2006",
    "lat": 58.8513138,
    "lon": 5.7369543,
    "lastUpdated": "2026-01-29T12:57:06Z"
  },
  {
    "id": "2331",
    "lineRef": "KOL:Line:8_1014",
    "lat": 58.9237352,
    "lon": 5.7263765,
    "lastUpdated": "2026-01-29T12:57:06Z"
  },
  {
    "id": "2336",
    "lineRef": "KOL:Line:8_1005",
    "lat": 58.9472258,
    "lon": 5.6805097,
    "lastUpdated": "2026-01-29T12:57:06Z"
  },
  {
    "id": "2337",
    "lineRef": "KOL:Line:8_1012",
    "lat": 58.938586,
    "lon": 5.5741687,
    "lastUpdated": "2026-01-29T12:57:06Z"
  },
  {
    "id": "2335",
    "lineRef": "KOL:Line:8_1025",
    "lat": 59.0107472,
    "lon": 5.6424197,
    "lastUpdated": "2026-01-29T12:57:06Z"
  },
  {
    "id": "2329",
    "lineRef": "KOL:Line:8_1043",
    "lat": 58.9537403,
    "lon": 5.7211577,
    "lastUpdated": "2026-01-29T12:57:06Z"
  },
  {
    "id": "2327",
    "lineRef": "KOL:Line:8_1005",
    "lat": 58.9687483,
    "lon": 5.75484,
    "lastUpdated": "2026-01-29T12:57:06Z"
  },
  {
    "id": "2328",
    "lineRef": "KOL:Line:8_1039",
    "lat": 58.952234,
    "lon": 5.6827337,
    "lastUpdated": "2026-01-29T12:57:06Z"
  },
  {
    "id": "2321",
    "lineRef": "KOL:Line:8_1014",
    "lat": 58.9521483,
    "lon": 5.7291133,
    "lastUpdated": "2026-01-29T12:57:06Z"
  },
  {
    "id": "2322",
    "lineRef": "KOL:Line:8_1005",
    "lat": 58.9706775,
    "lon": 5.7354623,
    "lastUpdated": "2026-01-29T12:57:06Z"
  },
  {
    "id": "2325",
    "lineRef": "KOL:Line:8_2005",
    "lat": 58.8663903,
    "lon": 5.7616387,
    "lastUpdated": "2026-01-29T12:57:06Z"
  },
  {
    "id": "2326",
    "lineRef": "KOL:Line:8_1032",
    "lat": 58.9630058,
    "lon": 5.7357675,
    "lastUpdated": "2026-01-29T12:57:06Z"
  },
  {
    "id": "2324",
    "lineRef": "KOL:Line:8_1506",
    "lat": 58.8705677,
    "lon": 5.6022233,
    "lastUpdated": "2026-01-29T12:57:06Z"
  },
  {
    "id": "2319",
    "lineRef": "KOL:Line:8_2006",
    "lat": 58.8283586,
    "lon": 5.7484265,
    "lastUpdated": "2026-01-29T12:57:06Z"
  },
  {
    "id": "2316",
    "lineRef": "KOL:Line:8_1005",
    "lat": 58.9497247,
    "lon": 5.7311427,
    "lastUpdated": "2026-01-29T12:57:06Z"
  },
  {
    "id": "2317",
    "lineRef": "KOL:Line:8_1039",
    "lat": 58.9317137,
    "lon": 5.7043325,
    "lastUpdated": "2026-01-29T12:57:06Z"
  },
  {
    "id": "2355",
    "lineRef": "KOL:Line:8_2008",
    "lat": 58.879264,
    "lon": 5.7737513,
    "lastUpdated": "2026-01-29T12:57:06Z"
  },
  {
    "id": "2352",
    "lineRef": "KOL:Line:8_1009",
    "lat": 58.9688581,
    "lon": 5.7107145,
    "lastUpdated": "2026-01-29T12:57:06Z"
  },
  {
    "id": "2353",
    "lineRef": "KOL:Line:8_1039",
    "lat": 58.9999985,
    "lon": 5.6186307,
    "lastUpdated": "2026-01-29T12:57:06Z"
  },
  {
    "id": "2356",
    "lineRef": "KOL:Line:8_1012",
    "lat": 58.8517503,
    "lon": 5.7364645,
    "lastUpdated": "2026-01-29T12:57:06Z"
  },
  {
    "id": "2350",
    "lineRef": "KOL:Line:8_1005",
    "lat": 58.9683002,
    "lon": 5.7561103,
    "lastUpdated": "2026-01-29T12:57:06Z"
  },
  {
    "id": "2351",
    "lineRef": "KOL:Line:8_1025",
    "lat": 58.9492055,
    "lon": 5.704319,
    "lastUpdated": "2026-01-29T12:57:06Z"
  },
  {
    "id": "2349",
    "lineRef": "KOL:Line:8_1025",
    "lat": 58.9522738,
    "lon": 5.688178,
    "lastUpdated": "2026-01-29T12:57:06Z"
  },
  {
    "id": "2341",
    "lineRef": "KOL:Line:8_1005",
    "lat": 58.949096,
    "lon": 5.7044702,
    "lastUpdated": "2026-01-29T12:57:06Z"
  },
  {
    "id": "2347",
    "lineRef": "KOL:Line:8_1021",
    "lat": 58.9531795,
    "lon": 5.6812448,
    "lastUpdated": "2026-01-29T12:57:05Z"
  },
  {
    "id": "2348",
    "lineRef": "KOL:Line:8_1014",
    "lat": 58.953819,
    "lon": 5.731476,
    "lastUpdated": "2026-01-29T12:57:06Z"
  },
  {
    "id": "2345",
    "lineRef": "KOL:Line:8_2006",
    "lat": 58.820689,
    "lon": 5.754188,
    "lastUpdated": "2026-01-29T12:57:05Z"
  },
  {
    "id": "2340",
    "lineRef": "KOL:Line:8_1043",
    "lat": 58.9669135,
    "lon": 5.734185,
    "lastUpdated": "2026-01-29T12:57:03Z"
  },
  {
    "id": "2338",
    "lineRef": "KOL:Line:8_1014",
    "lat": 58.9344973,
    "lon": 5.726597,
    "lastUpdated": "2026-01-29T12:57:06Z"
  },
  {
    "id": "5405",
    "lineRef": "KOL:Line:8_4602",
    "lat": 59.3405014,
    "lon": 6.0703035,
    "lastUpdated": "2026-01-29T12:57:06Z"
  },
  {
    "id": "258000810",
    "lineRef": "KOL:Line:8_5986",
    "lat": 59.15391666666667,
    "lon": 5.888816666666667,
    "lastUpdated": "2026-01-29T12:57:02.511Z"
  },
  {
    "id": "5448",
    "lineRef": "KOL:Line:8_3360",
    "lat": 59.5444015,
    "lon": 5.862442,
    "lastUpdated": "2026-01-29T12:57:06Z"
  },
  {
    "id": "5449",
    "lineRef": "KOL:Line:8_3359",
    "lat": 59.539353,
    "lon": 5.9750873,
    "lastUpdated": "2026-01-29T12:57:06Z"
  },
  {
    "id": "5433",
    "lineRef": "KOL:Line:8_4500",
    "lat": 59.51252352802022,
    "lon": 6.582300959104507,
    "lastUpdated": "2026-01-29T12:57:07Z"
  },
  {
    "id": "5465",
    "lineRef": "KOL:Line:8_3078",
    "lat": 59.6059885,
    "lon": 5.806119,
    "lastUpdated": "2026-01-29T12:52:42Z"
  },
  {
    "id": "5452",
    "lineRef": "KOL:Line:8_4631",
    "lat": 59.4862688,
    "lon": 5.978693,
    "lastUpdated": "2026-01-29T12:57:06Z"
  },
  {
    "id": "9832",
    "lineRef": "KOL:Line:8_2016",
    "lat": 58.7780162,
    "lon": 5.8321625,
    "lastUpdated": "2026-01-29T12:57:06Z"
  },
  {
    "id": "2431",
    "lineRef": "KOL:Line:8_1004",
    "lat": 58.9597238,
    "lon": 5.7069482,
    "lastUpdated": "2026-01-29T12:57:06Z"
  },
  {
    "id": "2430",
    "lineRef": "KOL:Line:8_1004",
    "lat": 58.9649673,
    "lon": 5.7344973,
    "lastUpdated": "2026-01-29T12:57:06Z"
  },
  {
    "id": "2428",
    "lineRef": "KOL:Line:8_1004",
    "lat": 58.9603465,
    "lon": 5.6314211,
    "lastUpdated": "2026-01-29T12:57:06Z"
  },
  {
    "id": "2429",
    "lineRef": "KOL:Line:8_1004",
    "lat": 58.892612,
    "lon": 5.7063457,
    "lastUpdated": "2026-01-29T12:57:06Z"
  },
  {
    "id": "2427",
    "lineRef": "KOL:Line:8_1004",
    "lat": 58.9686358,
    "lon": 5.6123902,
    "lastUpdated": "2026-01-29T12:57:06Z"
  },
  {
    "id": "2421",
    "lineRef": "KOL:Line:8_1004",
    "lat": 58.9609053,
    "lon": 5.6258353,
    "lastUpdated": "2026-01-29T12:57:06Z"
  },
  {
    "id": "2423",
    "lineRef": "KOL:Line:8_1004",
    "lat": 58.9700083,
    "lon": 5.5982857,
    "lastUpdated": "2026-01-29T12:57:06Z"
  },
  {
    "id": "259678000",
    "lineRef": "KOL:Line:8_5200",
    "lat": 58.97212666666667,
    "lon": 5.738513333333333,
    "lastUpdated": "2026-01-29T12:55:40.315Z"
  },
  {
    "id": "5502",
    "lineRef": "KOL:Line:8_3001",
    "lat": 59.3558658,
    "lon": 5.3159205,
    "lastUpdated": "2026-01-29T12:57:06Z"
  },
  {
    "id": "5503",
    "lineRef": "KOL:Line:8_3001",
    "lat": 59.3971804,
    "lon": 5.2977247,
    "lastUpdated": "2026-01-29T12:57:05Z"
  },
  {
    "id": "5501",
    "lineRef": "KOL:Line:8_3000",
    "lat": 59.4290625,
    "lon": 5.2726102,
    "lastUpdated": "2026-01-29T12:57:06Z"
  },
  {
    "id": "259386000",
    "lineRef": "KOL:Line:30_1130",
    "lat": 59.13805166666667,
    "lon": 5.588903333333334,
    "lastUpdated": "2026-01-29T12:57:01.202Z"
  },
  {
    "id": "5524",
    "lineRef": "KOL:Line:8_3010",
    "lat": 59.3991857,
    "lon": 5.284951,
    "lastUpdated": "2026-01-29T12:57:06Z"
  },
  {
    "id": "5526",
    "lineRef": "KOL:Line:8_3083",
    "lat": 59.3976848,
    "lon": 5.3279359,
    "lastUpdated": "2026-01-29T12:57:06Z"
  },
  {
    "id": "5521",
    "lineRef": "KOL:Line:8_3010",
    "lat": 59.288958,
    "lon": 5.3023422,
    "lastUpdated": "2026-01-29T12:57:06Z"
  },
  {
    "id": "5517",
    "lineRef": "KOL:Line:8_3001",
    "lat": 59.3947984,
    "lon": 5.3299945,
    "lastUpdated": "2026-01-29T12:54:15Z"
  },
  {
    "id": "5519",
    "lineRef": "KOL:Line:8_3318",
    "lat": 59.2194772,
    "lon": 5.1923038,
    "lastUpdated": "2026-01-29T12:57:06Z"
  },
  {
    "id": "5513",
    "lineRef": "KOL:Line:8_3000",
    "lat": 59.4129473,
    "lon": 5.2680352,
    "lastUpdated": "2026-01-29T12:57:06Z"
  },
  {
    "id": "5516",
    "lineRef": "KOL:Line:8_3000",
    "lat": 59.3946269,
    "lon": 5.3299253,
    "lastUpdated": "2026-01-29T12:52:59Z"
  },
  {
    "id": "5511",
    "lineRef": "KOL:Line:8_3000",
    "lat": 59.389292,
    "lon": 5.3344582,
    "lastUpdated": "2026-01-29T12:56:41Z"
  },
  {
    "id": "5506",
    "lineRef": "KOL:Line:8_3001",
    "lat": 59.3636764,
    "lon": 5.3068321,
    "lastUpdated": "2026-01-29T12:57:06Z"
  },
  {
    "id": "5508",
    "lineRef": "KOL:Line:8_3001",
    "lat": 59.4197693,
    "lon": 5.276269,
    "lastUpdated": "2026-01-29T12:57:06Z"
  },
  {
    "id": "5547",
    "lineRef": "KOL:Line:8_3060",
    "lat": 59.5441753,
    "lon": 5.8631082,
    "lastUpdated": "2026-01-29T12:57:06Z"
  },
  {
    "id": "5545",
    "lineRef": "KOL:Line:8_3026",
    "lat": 59.3897348,
    "lon": 5.3319817,
    "lastUpdated": "2026-01-29T12:57:05Z"
  },
  {
    "id": "5540",
    "lineRef": "KOL:Line:8_3010",
    "lat": 59.417036,
    "lon": 5.2730533,
    "lastUpdated": "2026-01-29T12:56:15Z"
  },
  {
    "id": "5541",
    "lineRef": "KOL:Line:8_3083",
    "lat": 59.4091468,
    "lon": 5.2741998,
    "lastUpdated": "2026-01-29T12:57:06Z"
  },
  {
    "id": "5539",
    "lineRef": "KOL:Line:8_3074",
    "lat": 59.5965706,
    "lon": 5.7427778,
    "lastUpdated": "2026-01-29T12:57:06Z"
  },
  {
    "id": "5535",
    "lineRef": "KOL:Line:8_3011",
    "lat": 59.3795833,
    "lon": 5.3054218,
    "lastUpdated": "2026-01-29T12:57:06Z"
  },
  {
    "id": "5536",
    "lineRef": "KOL:Line:8_3074",
    "lat": 59.3983005,
    "lon": 5.294315,
    "lastUpdated": "2026-01-29T12:57:06Z"
  },
  {
    "id": "5537",
    "lineRef": "KOL:Line:8_3353",
    "lat": 59.519108,
    "lon": 5.7184561,
    "lastUpdated": "2026-01-29T12:57:05Z"
  },
  {
    "id": "5531",
    "lineRef": "KOL:Line:8_3012",
    "lat": 59.2475748,
    "lon": 5.1995503,
    "lastUpdated": "2026-01-29T12:57:06Z"
  },
  {
    "id": "5534",
    "lineRef": "KOL:Line:8_3011",
    "lat": 59.3199508,
    "lon": 5.2902692,
    "lastUpdated": "2026-01-29T12:57:05Z"
  },
  {
    "id": "5530",
    "lineRef": "KOL:Line:8_3010",
    "lat": 59.2645743,
    "lon": 5.193789,
    "lastUpdated": "2026-01-29T12:57:06Z"
  },
  {
    "id": "5529",
    "lineRef": "KOL:Line:8_3074",
    "lat": 59.6387413,
    "lon": 5.9135812,
    "lastUpdated": "2026-01-29T12:57:06Z"
  },
  {
    "id": "5568",
    "lineRef": "KOL:Line:8_3011",
    "lat": 59.149861,
    "lon": 5.2615848,
    "lastUpdated": "2026-01-29T12:57:06Z"
  },
  {
    "id": "5569",
    "lineRef": "KOL:Line:8_3354",
    "lat": 59.5300847,
    "lon": 5.6892725,
    "lastUpdated": "2026-01-29T12:57:06Z"
  },
  {
    "id": "5557",
    "lineRef": "KOL:Line:8_3025",
    "lat": 59.2504793,
    "lon": 5.324673,
    "lastUpdated": "2026-01-29T12:57:06Z"
  },
  {
    "id": "5558",
    "lineRef": "KOL:Line:8_3029",
    "lat": 59.2931368,
    "lon": 5.2954692,
    "lastUpdated": "2026-01-29T12:57:05Z"
  },
  {
    "id": "5554",
    "lineRef": "KOL:Line:8_3375",
    "lat": 59.3425353,
    "lon": 5.2521612,
    "lastUpdated": "2026-01-29T12:57:06Z"
  },
  {
    "id": "5550",
    "lineRef": "KOL:Line:8_3000",
    "lat": 59.4107718,
    "lon": 5.287081,
    "lastUpdated": "2026-01-29T12:57:06Z"
  },
  {
    "id": "5552",
    "lineRef": "KOL:Line:8_3052",
    "lat": 59.4170882,
    "lon": 5.2732,
    "lastUpdated": "2026-01-29T12:57:06Z"
  },
  {
    "id": "5588",
    "lineRef": "KOL:Line:8_3001",
    "lat": 59.4182442,
    "lon": 5.297105,
    "lastUpdated": "2026-01-29T12:57:06Z"
  },
  {
    "id": "5585",
    "lineRef": "KOL:Line:8_3390",
    "lat": 59.5571317,
    "lon": 5.5664395,
    "lastUpdated": "2026-01-29T12:57:06Z"
  },
  {
    "id": "5579",
    "lineRef": "KOL:Line:8_3008",
    "lat": 59.3794243,
    "lon": 5.3061317,
    "lastUpdated": "2026-01-29T12:57:06Z"
  },
  {
    "id": "5577",
    "lineRef": "KOL:Line:8_3009",
    "lat": 59.4123423,
    "lon": 5.2712095,
    "lastUpdated": "2026-01-29T12:57:06Z"
  },
  {
    "id": "5574",
    "lineRef": "KOL:Line:8_3307",
    "lat": 59.441269,
    "lon": 5.552287,
    "lastUpdated": "2026-01-29T12:57:06Z"
  },
  {
    "id": "259216000",
    "lineRef": "KOL:Line:30_1130",
    "lat": 59.152965,
    "lon": 5.528363333333333,
    "lastUpdated": "2026-01-29T12:57:02.569Z"
  },
  {
    "id": "258271000",
    "lineRef": "KOL:Line:30_1130",
    "lat": 59.17099333333333,
    "lon": 5.45468,
    "lastUpdated": "2026-01-29T12:57:02.915Z"
  },
  {
    "id": "3026",
    "lineRef": "KOL:Line:8_2695",
    "lat": 58.4544868,
    "lon": 6.0025777,
    "lastUpdated": "2026-01-29T12:57:02Z"
  },
  {
    "id": "3023",
    "lineRef": "KOL:Line:8_2010",
    "lat": 58.8979011,
    "lon": 5.8456843,
    "lastUpdated": "2026-01-29T12:57:06Z"
  },
  {
    "id": "3027",
    "lineRef": "KOL:Line:8_2012",
    "lat": 58.7730025,
    "lon": 5.8763947,
    "lastUpdated": "2026-01-29T12:57:06Z"
  },
  {
    "id": "257640900",
    "lineRef": "KOL:Line:8_5200",
    "lat": 58.972968333333334,
    "lon": 5.737298333333333,
    "lastUpdated": "2026-01-29T04:27:25.989Z"
  },
  {
    "id": "3012",
    "lineRef": "KOL:Line:8_2033",
    "lat": 58.4535058,
    "lon": 6.0023605,
    "lastUpdated": "2026-01-29T12:49:34Z"
  },
  {
    "id": "3016",
    "lineRef": "KOL:Line:8_2608",
    "lat": 58.434213,
    "lon": 5.972541,
    "lastUpdated": "2026-01-29T12:57:06Z"
  },
  {
    "id": "3010",
    "lineRef": "KOL:Line:8_2029",
    "lat": 58.5832055,
    "lon": 6.0762867,
    "lastUpdated": "2026-01-29T12:57:06Z"
  },
  {
    "id": "3046",
    "lineRef": "KOL:Line:8_2013",
    "lat": 58.9468897,
    "lon": 5.8929597,
    "lastUpdated": "2026-01-29T12:57:06Z"
  },
  {
    "id": "3049",
    "lineRef": "KOL:Line:8_2011",
    "lat": 58.8514129,
    "lon": 5.735561,
    "lastUpdated": "2026-01-29T12:54:49Z"
  },
  {
    "id": "3044",
    "lineRef": "KOL:Line:8_2693",
    "lat": 58.862942669745934,
    "lon": 5.927220583345648,
    "lastUpdated": "2026-01-29T12:50:31Z"
  },
  {
    "id": "3033",
    "lineRef": "KOL:Line:8_2691",
    "lat": 58.832388,
    "lon": 5.6860385,
    "lastUpdated": "2026-01-29T12:57:06Z"
  },
  {
    "id": "3030",
    "lineRef": "KOL:Line:8_2667",
    "lat": 58.7384358,
    "lon": 5.6303952,
    "lastUpdated": "2026-01-29T12:57:06Z"
  },
  {
    "id": "3068",
    "lineRef": "KOL:Line:8_2036",
    "lat": 58.3919043,
    "lon": 6.0817895,
    "lastUpdated": "2026-01-29T12:57:06Z"
  },
  {
    "id": "3067",
    "lineRef": "KOL:Line:8_2017",
    "lat": 58.73652,
    "lon": 5.6851235,
    "lastUpdated": "2026-01-29T12:57:06Z"
  },
  {
    "id": "3066",
    "lineRef": "KOL:Line:8_2011",
    "lat": 58.7820038,
    "lon": 5.7293724,
    "lastUpdated": "2026-01-29T12:57:06Z"
  },
  {
    "id": "3065",
    "lineRef": "KOL:Line:8_2012",
    "lat": 58.8514215,
    "lon": 5.73713,
    "lastUpdated": "2026-01-29T12:57:05Z"
  },
  {
    "id": "3056",
    "lineRef": "KOL:Line:8_2024",
    "lat": 58.7720105,
    "lon": 5.6770478,
    "lastUpdated": "2026-01-29T12:55:11Z"
  },
  {
    "id": "3051",
    "lineRef": "KOL:Line:8_2693",
    "lat": 58.8316313,
    "lon": 5.9639148,
    "lastUpdated": "2026-01-29T12:53:29Z"
  },
  {
    "id": "3050",
    "lineRef": "KOL:Line:8_2035",
    "lat": 58.8513561,
    "lon": 5.7363242,
    "lastUpdated": "2026-01-29T12:57:06Z"
  },
  {
    "id": "3054",
    "lineRef": "KOL:Line:8_2600",
    "lat": 58.4451132,
    "lon": 6.005772,
    "lastUpdated": "2026-01-29T12:57:06Z"
  },
  {
    "id": "3052",
    "lineRef": "KOL:Line:8_2031",
    "lat": 58.5160685,
    "lon": 6.5112423,
    "lastUpdated": "2026-01-29T12:57:06Z"
  },
  {
    "id": "3086",
    "lineRef": "KOL:Line:8_2010",
    "lat": 58.854051,
    "lon": 5.7621646,
    "lastUpdated": "2026-01-29T12:57:06Z"
  },
  {
    "id": "3085",
    "lineRef": "KOL:Line:8_2019",
    "lat": 58.8513718,
    "lon": 5.7366503,
    "lastUpdated": "2026-01-29T12:57:06Z"
  },
  {
    "id": "3079",
    "lineRef": "KOL:Line:8_2602",
    "lat": 58.465125,
    "lon": 5.9481562,
    "lastUpdated": "2026-01-29T12:57:05Z"
  },
  {
    "id": "3073",
    "lineRef": "KOL:Line:8_2019",
    "lat": 58.7738108,
    "lon": 5.629536,
    "lastUpdated": "2026-01-29T12:57:06Z"
  },
  {
    "id": "3072",
    "lineRef": "KOL:Line:8_2040",
    "lat": 58.3899801,
    "lon": 6.0741167,
    "lastUpdated": "2026-01-29T12:57:05Z"
  },
  {
    "id": "3077",
    "lineRef": "KOL:Line:8_2012",
    "lat": 58.8050436,
    "lon": 5.7804765,
    "lastUpdated": "2026-01-29T12:57:06Z"
  },
  {
    "id": "3076",
    "lineRef": "KOL:Line:8_2012",
    "lat": 58.8507314,
    "lon": 5.7376642,
    "lastUpdated": "2026-01-29T12:56:25Z"
  },
  {
    "id": "3092",
    "lineRef": "KOL:Line:8_2632",
    "lat": 58.678409,
    "lon": 6.1575098,
    "lastUpdated": "2026-01-29T12:57:06Z"
  },
  {
    "id": "258001700",
    "lineRef": "KOL:Line:26_5958",
    "lat": 59.23479833333333,
    "lon": 6.165981666666667,
    "lastUpdated": "2026-01-29T12:57:02.334Z"
  },
  {
    "id": "3169",
    "lineRef": "KOL:Line:8_6140",
    "lat": 59.1505995,
    "lon": 6.1671875,
    "lastUpdated": "2026-01-29T12:57:06Z"
  },
  {
    "id": "3188",
    "lineRef": "KOL:Line:8_6100",
    "lat": 59.019189,
    "lon": 6.0395712,
    "lastUpdated": "2026-01-29T12:56:20Z"
  },
  {
    "id": "3183",
    "lineRef": "KOL:Line:8_6100",
    "lat": 59.030609,
    "lon": 6.0458685,
    "lastUpdated": "2026-01-29T12:57:06Z"
  },
  {
    "id": "3181",
    "lineRef": "KOL:Line:8_6101",
    "lat": 59.086464,
    "lon": 5.9183063,
    "lastUpdated": "2026-01-29T12:57:05Z"
  },
  {
    "id": "3186",
    "lineRef": "KOL:Line:8_6101",
    "lat": 59.0498957,
    "lon": 5.9216532,
    "lastUpdated": "2026-01-29T12:57:06Z"
  },
  {
    "id": "3178",
    "lineRef": "KOL:Line:8_6100",
    "lat": 58.9715627,
    "lon": 5.7400158,
    "lastUpdated": "2026-01-29T12:57:06Z"
  },
  {
    "id": "3172",
    "lineRef": "KOL:Line:8_6209",
    "lat": 59.0368558,
    "lon": 5.9354107,
    "lastUpdated": "2026-01-29T12:55:34Z"
  },
  {
    "id": "3171",
    "lineRef": "KOL:Line:8_6100",
    "lat": 59.04547158867515,
    "lon": 5.853402403813853,
    "lastUpdated": "2026-01-29T12:57:07Z"
  },
  {
    "id": "3170",
    "lineRef": "KOL:Line:8_6405",
    "lat": 59.1550858,
    "lon": 6.1942358,
    "lastUpdated": "2026-01-29T12:57:06Z"
  },
  {
    "id": "3191",
    "lineRef": "KOL:Line:8_6304",
    "lat": 59.0241295,
    "lon": 6.00935,
    "lastUpdated": "2026-01-29T12:57:06Z"
  },
  {
    "id": "3198",
    "lineRef": "KOL:Line:8_6122",
    "lat": 58.8872278,
    "lon": 6.1439507,
    "lastUpdated": "2026-01-29T12:57:06Z"
  },
  {
    "id": "3190",
    "lineRef": "KOL:Line:8_6100",
    "lat": 59.0340442,
    "lon": 5.9410175,
    "lastUpdated": "2026-01-29T12:57:06Z"
  }
]