[
  {
    "id": "258009600",
    "lineRef": "KOL:Line:8_5200",
    "lat": 58.9364485,
    "lon": 5.8255423,
    "lastUpdated": "2026-02-06T04:46:11Z"
  },
  {
    "id": "3271",
    "lineRef": "KOL:Line:8_6120",
    "lat": 59.0168145,
    "lon": 6.0477995,
    "lastUpdated": "2026-02-06T04:46:11Z"
  },
  {
    "id": "258002060",
    "lineRef": "KOL:Line:26_5958",
    "lat": 59.250165,
    "lon": 6.165895000000001,
    "lastUpdated": "2026-02-06T04:46:09.222Z"
  },
  {
    "id": "3308",
    "lineRef": "KOL:Line:8_2011",
    "lat": 58.8514295,
    "lon": 5.7355587,
    "lastUpdated": "2026-02-06T04:45:07Z"
  },
  {
    "id": "2003",
    "lineRef": "KOL:Line:8_1006",
    "lat": 58.9130178,
    "lon": 5.6950722,
    "lastUpdated": "2026-02-06T04:46:11Z"
  },
  {
    "id": "2006",
    "lineRef": "KOL:Line:8_1002",
    "lat": 58.9012418,
    "lon": 5.6931287,
    "lastUpdated": "2026-02-06T04:42:58Z"
  },
  {
    "id": "258021190",
    "lineRef": "KOL:Line:8_5961",
    "lat": 59.344998333333336,
    "lon": 5.857761666666667,
    "lastUpdated": "2026-02-05T18:10:57.611Z"
  },
  {
    "id": "2109",
    "lineRef": "KOL:Line:8_1013",
    "lat": 59.1190635,
    "lon": 5.7185128,
    "lastUpdated": "2026-02-06T04:46:11Z"
  },
  {
    "id": "2108",
    "lineRef": "KOL:Line:8_1017",
    "lat": 59.0599412,
    "lon": 5.6926732,
    "lastUpdated": "2026-02-06T04:46:11Z"
  },
  {
    "id": "2208",
    "lineRef": "KOL:Line:8_1007",
    "lat": 58.9684188,
    "lon": 5.7310345,
    "lastUpdated": "2026-02-06T04:46:11Z"
  },
  {
    "id": "2209",
    "lineRef": "KOL:Line:8_1002",
    "lat": 58.8516195,
    "lon": 5.7362842,
    "lastUpdated": "2026-02-06T04:46:11Z"
  },
  {
    "id": "2206",
    "lineRef": "KOL:Line:8_1000",
    "lat": 59.0011698,
    "lon": 5.7238835,
    "lastUpdated": "2026-02-06T04:46:11Z"
  },
  {
    "id": "2200",
    "lineRef": "KOL:Line:8_1002",
    "lat": 58.9120541,
    "lon": 5.7267561,
    "lastUpdated": "2026-02-06T04:46:11Z"
  },
  {
    "id": "2201",
    "lineRef": "KOL:Line:8_1007",
    "lat": 58.856442,
    "lon": 5.7410725,
    "lastUpdated": "2026-02-06T04:46:11Z"
  },
  {
    "id": "2204",
    "lineRef": "KOL:Line:8_1006",
    "lat": 58.9226201,
    "lon": 5.7075363,
    "lastUpdated": "2026-02-06T04:46:10Z"
  },
  {
    "id": "2205",
    "lineRef": "KOL:Line:8_1002",
    "lat": 58.8768656,
    "lon": 5.7250618,
    "lastUpdated": "2026-02-06T04:46:11Z"
  },
  {
    "id": "2203",
    "lineRef": "KOL:Line:8_1002",
    "lat": 58.9266202,
    "lon": 5.7344333,
    "lastUpdated": "2026-02-06T04:46:11Z"
  },
  {
    "id": "258000840",
    "lineRef": "KOL:Line:8_5986",
    "lat": 59.229490000000006,
    "lon": 5.923241666666667,
    "lastUpdated": "2026-02-06T04:46:09.005Z"
  },
  {
    "id": "258223000",
    "lineRef": "KOL:Line:30_1130",
    "lat": 59.13819,
    "lon": 5.587788333333333,
    "lastUpdated": "2026-02-05T19:39:59.198Z"
  },
  {
    "id": "2308",
    "lineRef": "KOL:Line:8_1006",
    "lat": 58.9902635,
    "lon": 5.6559723,
    "lastUpdated": "2026-02-06T04:37:52Z"
  },
  {
    "id": "2300",
    "lineRef": "KOL:Line:8_1012",
    "lat": 58.8945279,
    "lon": 5.7008225,
    "lastUpdated": "2026-02-06T04:46:11Z"
  },
  {
    "id": "2303",
    "lineRef": "KOL:Line:8_1012",
    "lat": 58.8567617,
    "lon": 5.741846,
    "lastUpdated": "2026-02-06T04:46:11Z"
  },
  {
    "id": "2304",
    "lineRef": "KOL:Line:8_1008",
    "lat": 58.9659875,
    "lon": 5.7315323,
    "lastUpdated": "2026-02-06T04:46:10Z"
  },
  {
    "id": "258000810",
    "lineRef": "KOL:Line:8_5986",
    "lat": 59.138385,
    "lon": 5.89774,
    "lastUpdated": "2026-02-06T04:45:58.488Z"
  },
  {
    "id": "257144700",
    "lineRef": "KOL:Line:30_1130",
    "lat": 59.14955166666667,
    "lon": 5.552725,
    "lastUpdated": "2026-02-06T04:46:08.611Z"
  },
  {
    "id": "259678000",
    "lineRef": "KOL:Line:8_5200",
    "lat": 58.97311333333334,
    "lon": 5.740086666666667,
    "lastUpdated": "2026-02-05T16:48:28.561Z"
  },
  {
    "id": "259386000",
    "lineRef": "KOL:Line:30_1130",
    "lat": 59.17147666666666,
    "lon": 5.465051666666667,
    "lastUpdated": "2026-02-05T23:02:49.527Z"
  },
  {
    "id": "5549",
    "lineRef": "KOL:Line:8_3011",
    "lat": 59.2667738,
    "lon": 5.1950059,
    "lastUpdated": "2026-02-06T04:46:10Z"
  },
  {
    "id": "5529",
    "lineRef": "KOL:Line:8_3074",
    "lat": 59.5307212,
    "lon": 5.6876955,
    "lastUpdated": "2026-02-06T04:46:11Z"
  },
  {
    "id": "345",
    "lineRef": "KOL:Line:8_1018",
    "lat": 59.0517248,
    "lon": 5.667496,
    "lastUpdated": "2026-02-06T04:46:11Z"
  },
  {
    "id": "346",
    "lineRef": "KOL:Line:8_1013",
    "lat": 59.0990422,
    "lon": 5.7004115,
    "lastUpdated": "2026-02-06T04:46:11Z"
  },
  {
    "id": "349",
    "lineRef": "KOL:Line:8_1013",
    "lat": 59.0938903,
    "lon": 5.7533363,
    "lastUpdated": "2026-02-06T04:46:09Z"
  },
  {
    "id": "258271000",
    "lineRef": "KOL:Line:30_1130",
    "lat": 59.165036666666666,
    "lon": 5.5090916666666665,
    "lastUpdated": "2026-02-06T04:46:08.917Z"
  },
  {
    "id": "3029",
    "lineRef": "KOL:Line:8_2012",
    "lat": 58.7665583,
    "lon": 5.8620253,
    "lastUpdated": "2026-02-06T04:46:11Z"
  },
  {
    "id": "257640900",
    "lineRef": "KOL:Line:8_5200",
    "lat": 58.97205333333333,
    "lon": 5.73848,
    "lastUpdated": "2026-02-06T04:05:43.1Z"
  },
  {
    "id": "3046",
    "lineRef": "KOL:Line:8_2010",
    "lat": 58.9305968,
    "lon": 5.8436028,
    "lastUpdated": "2026-02-06T04:46:11Z"
  },
  {
    "id": "3045",
    "lineRef": "KOL:Line:8_2002",
    "lat": 58.4570005,
    "lon": 5.9091553,
    "lastUpdated": "2026-02-06T04:46:10Z"
  },
  {
    "id": "3031",
    "lineRef": "KOL:Line:8_2010",
    "lat": 58.850841,
    "lon": 5.73745,
    "lastUpdated": "2026-02-06T04:39:11Z"
  },
  {
    "id": "3082",
    "lineRef": "KOL:Line:8_2017",
    "lat": 58.735065,
    "lon": 5.6489758,
    "lastUpdated": "2026-02-06T04:41:17Z"
  },
  {
    "id": "3081",
    "lineRef": "KOL:Line:8_2024",
    "lat": 58.7738739,
    "lon": 5.6296341,
    "lastUpdated": "2026-02-06T04:46:11Z"
  },
  {
    "id": "3078",
    "lineRef": "KOL:Line:8_2040",
    "lat": 58.3743503,
    "lon": 6.246004,
    "lastUpdated": "2026-02-06T04:46:11Z"
  },
  {
    "id": "3070",
    "lineRef": "KOL:Line:8_2011",
    "lat": 58.780965,
    "lon": 5.72561,
    "lastUpdated": "2026-02-06T04:46:10Z"
  },
  {
    "id": "258001700",
    "lineRef": "KOL:Line:26_5958",
    "lat": 59.23492666666667,
    "lon": 6.166085,
    "lastUpdated": "2026-02-05T20:53:16.673Z"
  },
  {
    "id": "3185",
    "lineRef": "KOL:Line:8_6100",
    "lat": 58.9988941,
    "lon": 5.7216301,
    "lastUpdated": "2026-02-06T04:46:11Z"
  },
  {
    "id": "3177",
    "lineRef": "KOL:Line:8_6101",
    "lat": 59.0864693,
    "lon": 5.9183117,
    "lastUpdated": "2026-02-06T04:46:11Z"
  },
  {
    "id": "3171",
    "lineRef": "KOL:Line:8_6100",
    "lat": 59.0336997,
    "lon": 6.0369172,
    "lastUpdated": "2026-02-06T04:46:11Z"
  },
  {
    "id": "3170",
    "lineRef": "KOL:Line:8_6140",
    "lat": 59.1684918,
    "lon": 6.1402823,
    "lastUpdated": "2026-02-06T04:46:11Z"
  },
  {
    "id": "3191",
    "lineRef": "KOL:Line:8_6100",
    "lat": 59.017628,
    "lon": 6.0431017,
    "lastUpdated": "2026-02-06T04:46:01Z"
  }
]